Workbook

Sheet SOIC
A1: JSE:SOL
A2: Sasol
A3: Income Statement | B3: ZAR | C3: ZAR | D3: ZAR | E3: ZAR | F3: ZAR
B4: 2020 | C4: 2021 | D4: 2022 | E4: 2023 | F4: 2024
A5: Turnover | B5: 190367000 | C5: 201910000 | D5: 272746000 | E5: 289696000 | F5: 275111000
A6: % Change in Turnover | B6: - | C6: =(C5-B5)/B5 *100 -> 6.0635509 | D6: =(D5-C5)/C5 *100 -> 35.082958 | E6: =(E5-D5)/D5 *100 -> 6.2145733 | F6: =(F5-E5)/E5 *100 -> -5.034588
A7: Cost of Sales | B7: 100602000 | C7: 97485000 | D7: 137321000 | E7: 167373000 | F7: 153403000
A8: Gross Profit | B8: 89765000 | C8: 104425000 | D8: 135425000 | E8: 122323000 | F8: 121708000
A9: Total Income | B9: 89765000 | C9: 104425000 | D9: 135425000 | E9: 122323000 | F9: 121708000
A11: Selling General & Admin Exp. | B11: 39119000 | C11: 40932000 | D11: 41164000 | E11: 44063000 | F11: 45915000
A12: Exploration/Drilling Costs | B12: 608000 | C12: NA | D12: NA | E12: NA | F12: NA
A13: Depreciation & Amort. | B13: 22327000 | C13: 17644000 | D13: 14073000 | E13: 16491000 | F13: 15644000
A14: Impair. of Oil, Gas & Mineral Prop. | B14: -43000 | C14: 6000 | D14: NA | E14: 899000 | F14: 48000
A15: Other Operating Expense | B15: 14437000 | C15: 20203000 | D15: 29789000 | E15: 7173000 | F15: 15436000
A16: Other Operating Exp., Total | B16: 76448000 | C16: 78785000 | D16: 85026000 | E16: 68626000 | F16: 77043000
A17: Operating Income | B17: 13317000 | C17: 25640000 | D17: 50399000 | E17: 53697000 | F17: 44665000
A19: Interest Expense | B19: -7352000 | C19: -6711000 | D19: -5772000 | E19: -9113000 | F19: -10224000
A20: Interest and Invest. Income | B20: 922000 | C20: 856000 | D20: 1020000 | E20: 2253000 | F20: 3226000
A21: Net Interest Exp. | B21: -6430000 | C21: -5855000 | D21: -4752000 | E21: -6860000 | F21: -6998000
A22: Income from Affiliates | B22: -347000 | C22: 814000 | D22: 3128000 | E22: 2623000 | F22: 1758000
A23: Currency Exchange Gains | B23: -12774000 | C23: 13414000 | D23: -3042000 | E23: -1801000 | F23: 1638000
A24: Other Non-Operating Inc. | B24: 1141000 | C24: -84000 | D24: -169000 | E24: -146000 | F24: -203000
A25: EBT Excl Unusual Items | B25: -5093000 | C25: 33929000 | D25: 45564000 | E25: 47513000 | F25: 40860000
A26: Gain (Loss) On Sale Of Invest. | B26: NA | C26: -112000 | D26: NA | E26: NA | F26: NA
A27: Gain (Loss) On Sale Of Assets | B27: 715000 | C27: 5520000 | D27: 8460000 | E27: 650000 | F27: -480000
A28: Asset Writedown | B28: -112736000 | C28: -28620000 | D28: 1443000 | E28: -33649000 | F28: -74886000
A29: Other Unusual Items | B29: -1193000 | C29: NA | D29: 74000 | E29: NA | F29: NA
A30: EBT Incl. Unusual Items | B30: -118307000 | C30: 10717000 | D30: 55541000 | E30: 14514000 | F30: -34506000
A32: Income Tax Expense | B32: -26390000 | C32: 185000 | D32: 13869000 | E32: 5181000 | F32: 9739000
A33: Earnings from Cont. Ops. | B33: -91917000 | C33: 10532000 | D33: 41672000 | E33: 9333000 | F33: -44245000
A34: Net Income to Company | B34: -91917000 | C34: 10532000 | D34: 41672000 | E34: 9333000 | F34: -44245000
A35: Minority Int. in Earnings | B35: 163000 | C35: -1500000 | D35: -2716000 | E35: -534000 | F35: -26000
A36: Net Income | B36: -91754000 | C36: 9032000 | D36: 38956000 | E36: 8799000 | F36: -44271000
A37: NI to Common Incl Extra Items | B37: -91754000 | C37: 9032000 | D37: 38956000 | E37: 8799000 | F37: -44271000
A38: NI to Common Excl. Extra Items | B38: -91754000 | C38: 9032000 | D38: 38956000 | E38: 8799000 | F38: -44271000
A39: Per Share Items (R)
A40: Basic EPS | B40: -148.493 | C40: 14.57 | D40: 62.34 | E40: 14.002 | F40: -69.938
A41: Basic EPS Excl. Extra Items | B41: -148.493 | C41: 14.57 | D41: 62.34 | E41: 14.002 | F41: -69.938
A42: Weighted Avg. Basic Shares Out. (actual) | B42: 617900000 | C42: 619900000 | D42: 624900000 | E42: 628400000 | F42: 633000000
A43: Diluted EPS Incl. Extra Items | B43: -148.493 | C43: 14.39 | D43: 61.36 | E43: 13.023 | F43: -69.94
A44: Diluted EPS Excl. Extra Items | B44: -148.493 | C44: 14.39 | D44: 61.36 | E44: 13.023 | F44: -69.94
A45: Weighted Avg. Diluted Shares Out. (actual) | B45: 617900000 | C45: 627800000 | D45: 634900000 | E45: 661900000 | F45: 633000000
A46: Normalized Basic EPS | B46: -4.888 | C46: 31.788 | D46: 41.225 | E46: 46.406 | F46: 40.303
A47: Normalized Diluted EPS | B47: -4.888 | C47: 31.388 | D47: 40.576 | E47: 44.057 | F47: 40.303
A48: Dividends per Share | B48: NA | C48: NA | D48: 14.7 | E48: 17 | F48: 2
A49: Payout Ratio (%) | B49: NM | C49: 0.509 | D49: 0.126 | E49: 156.313 | F49: NM
A50: Shares per Depositary Receipt (actual) | B50: 1 | C50: 1 | D50: 1 | E50: 1 | F50: 1 | Q50: 2020 | R50: 2021 | S50: 2022 | T50: 2023 | U50: 2024
A51: Supplemental Items (R000) | P51: EBITDA | Q51: 35601000 | R51: 43290000 | S51: 64472000 | T51: 68737000 | U51: 57879000
A52: EBITDA | B52: 35601000 | C52: 43290000 | D52: 64472000 | E52: 68737000 | F52: 57879000 | P52: Turnover | Q52: 190367000 | R52: 201910000 | S52: 272746000 | T52: 289696000 | U52: 275111000
A53: EBITA | B53: 13317000 | C53: 25640000 | D53: 50399000 | E53: 53697000 | F53: 44665000
A54: EBIT | B54: 13317000 | C54: 25640000 | D54: 50399000 | E54: 53697000 | F54: 44665000
A55: EBITDAR | B55: 36455000 | C55: 43836000 | D55: 65057000 | E55: 69469000 | F55: 58643000
A56: Effective Tax Rate (%) | B56: 22.306 | C56: 1.726 | D56: 24.971 | E56: 35.697 | F56: NM
A57: Current Domestic Taxes | B57: NA | C57: 7430000 | D57: NA | E57: 10271000 | F57: 8128000
A58: Current Foreign Taxes | B58: NA | C58: 2079000 | D58: NA | E58: 2654000 | F58: 2028000
A59: Total Current Taxes | B59: 930000 | C59: 9509000 | D59: 16231000 | E59: 12925000 | F59: 10156000
A60: Deferred Domestic Taxes | B60: -9324000 | C60: -9779000 | D60: -2535000 | E60: -4721000 | F60: 709000
A61: Deferred Foreign Taxes | B61: -17996000 | C61: 455000 | D61: 173000 | E61: -3023000 | F61: -1126000
A62: Total Deferred Taxes | B62: -27320000 | C62: -9324000 | D62: -2362000 | E62: -7744000 | F62: -417000
A63: Normalized Net Income | B63: -3020125 | C63: 19705625 | D63: 25761500 | E63: 29161625 | F63: 25511500
A64: Interest on Long-Term Debt | B64: 1600000 | C64: 1648000 | D64: 1489000 | E64: 3336000 | F64: 3269000
A65: Supplemental Operating Expense Items (R000)
A66: Selling and Marketing Expense | B66: 8388000 | C66: 8026000 | D66: 8677000 | E66: 10470000 | F66: 10394000
A67: Exploration/Drilling Expenses | B67: 608000 | C67: NA | D67: NA | E67: NA | F67: NA
A68: Net Rental Expense, Total | B68: 854000 | C68: 546000 | D68: 585000 | E68: 732000 | F68: 764000
A69: Imputed Oper. Lease Interest Exp. | B69: 429240.9 | C69: 203374.08 | D69: 254236.32 | E69: 455854.46 | F69: 526090.4
A70: Imputed Oper. Lease Depreciation | B70: 424759.1 | C70: 342625.92 | D70: 330763.68 | E70: 276145.54 | F70: 237909.6
A71: Maintenance & Repair Expenses | B71: 10493000 | C71: 12115000 | D71: 13322000 | E71: 15076000 | F71: 15446000
A72: Stock-Based Comp., SG&A Exp. | B72: 1946000 | C72: 1927000 | D72: 1164000 | E72: 1033000 | F72: 986000
A73: Stock-Based Comp., Total | B73: 1946000 | C73: 1927000 | D73: 1164000 | E73: 1033000 | F73: 986000
A74: CIQ Restatement Type Code | B74: RS | C74: RC | D74: RC | E74: RC | F74: O
A75: CIQ Calculation Type Code | B75: REP | C75: REP | D75: REP | E75: REP | F75: REP
A76: Options Outstanding
A77: Options Out. at the Begin of Period, Common Stock | B77: NA | C77: NA | D77: NA | E77: 14262197 | F77: 11923890
A78: Options Granted During the Period, Common Stock | B78: NA | C78: NA | D78: NA | E78: 3179896 | F78: 5096901
A79: Options Exercised During the Period, Common Stock | B79: NA | C79: NA | D79: NA | E79: 4862497 | F79: 5269601
A80: Options Cancelled During the Period, Common Stock | B80: NA | C80: NA | D80: NA | E80: 655706 | F80: 757993
A81: Options Out. at the End of Period, Common Stock | B81: NA | C81: NA | D81: NA | E81: 11923890 | F81: 10993197
A82: Options Outstanding - All Classes
A83: Options Out. at the Beginning of the Period, Total | B83: NA | C83: NA | D83: NA | E83: 14262197 | F83: 11923890
A84: Options Granted During the Period, Total | B84: NA | C84: NA | D84: NA | E84: 3179896 | F84: 5096901
A85: Options Exercised During the Period, Total | B85: NA | C85: NA | D85: NA | E85: 4862497 | F85: 5269601
A86: Options Cancelled During the Period, Total | B86: NA | C86: NA | D86: NA | E86: 655706 | F86: 757993
A87: Options Out. at the End of the Period, Total | B87: NA | C87: NA | D87: NA | E87: 11923890 | F87: 10993197
A88: Stock Based Compensation (R000)
A89: Stock Based Comp. Exp., Before Tax | B89: 1946000 | C89: 1927000 | D89: 1164000 | E89: 1033000 | F89: 986000
A90: Capitalized Interest Data (R000)
A91: Interest Capitalized During the Period | B91: 3520000 | C91: 880000 | D91: 740000 | E91: 1074000 | F91: 1644000

Sheet SOCI
A1: JSE:SOL
A2: SASOL
A4: Statement of Comprehensive Income | B4: ZAR | C4: ZAR | D4: ZAR | E4: ZAR | F4: ZAR
B5: 2020 (Rm) | C5: 2021(Rm) | D5: 2022(Rm) | E5: 2023(Rm) | F5: 2024(Rm)
A6: Earnings for the year | B6: -91917 | C6: 10532 | D6: 41672 | E6: 15453 | F6: 15099
A8: Other Comprehensive income, net of tax
A9: Items that cannot be subsequently reclassified to the income statement | B9: -205 | C9: 623 | D9: 1616 | E9: 117 | F9: -76
A10: Remeasurement on post-retirement benefit obligation | B10: -147 | C10: 834 | D10: 2415 | E10: 161 | F10: -106
A11: Tax on items that cannot be subsequently reclassified to the income statement | B11: 54 | C11: -119 | D11: -745 | E11: -44 | F11: 30
A12: Fair value of investments through other comprehensive income | B12: -112 | C12: -12 | D12: -54
A14: Items that can be subsequently reclassified to the income statement | B14: 24123 | C14: -16246 | D14: -92 | E14: - | F14: -
A15: Effect of translation of foreign operations | B15: 26720 | C15: -13741 | D15: 7026 | E15: - | F15: -
A16: Effect of cash flow hedges | B16: -2192 | C16: 1072 | D16: 1110 | E16: - | F16: -
A17: Foreign currency translation reserve on disposal of business reclassified to the income statement | B17: -801 | C17: -3388 | D17: -8024 | E17: - | F17: -
A18: Tax on items that can be subsequently reclassified to the income statement | B18: 396 | C18: -189 | D18: -204 | E18: - | F18: -
A21: Total comprehensive incone for the year | B21: -67999 | C21: -5091 | D21: 43196 | E21: 15570 | F21: 15023
A22: Attributable to
A23: Owners of Sasol South Africa Limited | B23: -67865 | C23: -6578 | D23: 40485 | E23: - | F23: -
A24: Non-controlling interests in subsidiaries | B24: -134 | C24: 1487 | D24: 2711 | E24: - | F24: -
B25: -67999 | C25: -5091 | D25: 43196 | E25: 15570 | F25: 15023

Sheet SOFP
A1: JSE:SOL
A2: SASOL GROUP LIMITED
A4: Statement of Financial Position | B4: ZAR | C4: ZAR | D4: ZAR | E4: ZAR | F4: ZAR
B5: 2020 | C5: 2021 | D5: 2022 | E5: 2023 | F5: 2024
A6: Assets (R000)
A7: Cash and Equivalents | B7: 34739000 | C7: 31231000 | D7: 43140000 | E7: 53926000 | F7: 45383000
A8: Trading Asset Securities | B8: NA | C8: NA | D8: NA | E8: 1237000 | F8: 2173000
A9: Cash & Short-term Investments | B9: 34739000 | C9: 31231000 | D9: 43140000 | E9: 55163000 | F9: 47556000
A10: Accounts Receivable | B10: 17907000 | C10: 23440000 | D10: 32316000 | E10: 26544000 | F10: 27443000
A11: Other Receivables | B11: 11004000 | C11: 6746000 | D11: 12972000 | E11: 7265000 | F11: 7993000
A12: Total Receivables | B12: 28911000 | C12: 30186000 | D12: 45288000 | E12: 33809000 | F12: 35436000
A13: Inventory | B13: 27801000 | C13: 29742000 | D13: 41110000 | E13: 42205000 | F13: 40719000
A14: Prepaid Exp. | B14: 1605000 | C14: 1860000 | D14: 2115000 | E14: 2507000 | F14: 1553000
A15: Other Current Assets | B15: 84913000 | C15: 12145000 | D15: 603000 | E15: 845000 | F15: 1457000
A16: Total Current Assets | B16: 177969000 | C16: 105164000 | D16: 132256000 | E16: 134529000 | F16: 126721000
A17: Gross Property, Plant & Equipment | B17: 481833000 | C17: 451484000 | D17: 482019000 | E17: 530341000 | F17: 541529000
A18: Accumulated Depreciation | B18: -240372000 | C18: -240560000 | D18: -248082000 | E18: -293184000 | F18: -365589000
A19: Net Property, Plant & Equipment | B19: 241461000 | C19: 210924000 | D19: 233937000 | E19: 237157000 | F19: 175940000
A20: Long-term Investments | B20: 15107000 | C20: 12795000 | D20: 15131000 | E20: 16968000 | F20: 17278000
... A25: Total Assets | B25: 474535000 | C25: 360743000 | D25: 419548000 | E25: 433838000 | F25: 364980000
A26: Liabilities (R000)
A27: Accounts Payable | B27: 13535000 | C27: 17197000 | D27: 26888000 | E27: 26311000 | F27: 24972000
A28: Accrued Exp. | B28: 11747000 | C28: 9779000 | D28: 10005000 | E28: 9597000 | F28: 8752000
A29: Short-term Borrowings | B29: 22533000 | C29: 303000 | D29: 255000 | E29: 238000 | F29: 687000
A30: Curr. Port. of LT Debt | B30: 19686000 | C30: 5506000 | D30: 22334000 | E30: 41749000 | F30: 1118000
A31: Current Portion of Leases | B31: 1894000 | C31: 1771000 | D31: 1768000 | E31: 1915000 | F31: 2264000
A32: Curr. Income Taxes Payable | B32: 665000 | C32: 806000 | D32: 3142000 | E32: 1876000 | F32: 1108000
A33: Unearned Revenue, Current | B33: 579000 | C33: 576000 | D33: 724000 | E33: 966000 | F33: 320000
A34: Other Current Liabilities | B34: 22479000 | C34: 21626000 | D34: 26659000 | E34: 19395000 | F34: 15274000
A35: Total Current Liabilities | B35: 93118000 | C35: 57564000 | D35: 91775000 | E35: 102047000 | F35: 54495000
A36: Long-Term Debt | B36: 147511000 | C36: 97137000 | D36: 82500000 | E36: 82319000 | F36: 115913000
A37: Long-Term Leases | B37: 15825000 | C37: 13906000 | D37: 14266000 | E37: 14382000 | F37: 15173000
A38: Unearned Revenue, Non-Current | B38: 842000 | C38: 400000 | D38: 372000 | E38: 465000 | F38: 446000
... A42: Total Liabilities | B42: 318618000 | C42: 208272000 | D42: 226351000 | E42: 232314000 | F42: 217553000
A43: Equity (R000)
A44: Common Stock | B44: 9888000 | C44: 9888000 | D44: 9888000 | E44: 9888000 | F44: 9888000
A45: Retained Earnings | B45: 87559000 | C45: 99516000 | D45: 139251000 | E45: 135706000 | F45: 84537000
A46: Comprehensive Inc. and Other | B46: 53529000 | C46: 37085000 | D46: 39484000 | E46: 51310000 | F46: 48580000
A47: Total Common Equity | B47: 150976000 | C47: 146489000 | D47: 188623000 | E47: 196904000 | F47: 143005000
A48: Total Minority Interest | B48: 4941000 | C48: 5982000 | D48: 4574000 | E48: 4620000 | F48: 4422000
A49: Total Equity | B49: 155917000 | C49: 152471000 | D49: 193197000 | E49: 201524000 | F49: 147427000
A50: Total Liabilities And Equity | B50: 474535000 | C50: 360743000 | D50: 419548000 | E50: 433838000 | F50: 364980000
A51: Supplemental Items (R)
A52: ECS Total Shares Outstanding on Filing Date (actual) | B52: 627887189 | C52: 629765768 | D52: 631203721 | E52: 630293924 | F52: 635419278
A53: ECS Total Common Shares Outstanding (actual) | B53: 627887189 | C53: 629765768 | D53: 631203721 | E53: 630293924 | F53: 635419278 | H53: Market cap | I53: =132.2*B53 -> 8.3006686e+10 | J53: =(218.01)*C53 -> 1.3729524e+11 | K53: =371.68 * D53 -> 2.346058e+11 | L53: =233.26 * E53 -> 1.4702236e+11 | M53: =138 * F53 -> 87687860364
A54: Book Value per Share | B54: 240.451 | C54: 232.609 | D54: 298.831 | E54: 312.4 | F54: 225.056
A55: Tangible Book Value | B55: 148176000 | C55: 144007000 | D55: 185572000 | E55: 193713000 | F55: 140543000
A56: Tangible Book Value per Share | B56: 235.991 | C56: 228.668 | D56: 293.997 | E56: 307.338 | F56: 221.182
A57: Total Debt | B57: 207449000 | C57: 118623000 | D57: 121123000 | E57: 140603000 | F57: 135155000
A58: Net Debt | B58: 172710000 | C58: 87392000 | D58: 77983000 | E58: 85440000 | F58: 87599000
A59: Debt Equiv. of Unfunded Proj. Benefit Obligation | B59: 8429000 | C59: 5919000 | D59: 437000 | E59: 2287000 | F59: -102000
A60: Debt Equivalent Oper. Leases | B60: 6832000 | C60: 4368000 | D60: 4680000 | E60: 5856000 | F60: 6112000
A61: Total Minority Interest | B61: 4941000 | C61: 5982000 | D61: 4574000 | E61: 4620000 | F61: 4422000
A62: Equity Method Investments | B62: 11812000 | C62: 10142000 | D62: 12684000 | E62: 14804000 | F62: 14742000
A63: Raw Materials Inventory | B63: 5381000 | C63: 6103000 | D63: 8594000 | E63: 8842000 | F63: 8489000
A64: Work in Progress Inventory | B64: 2108000 | C64: 2560000 | D64: 2661000 | E64: 2614000 | F64: 3012000
A65: Finished Goods Inventory | B65: 13936000 | C65: 15494000 | D65: 24219000 | E65: 23860000 | F65: 21464000
... A73: Accumulated Allowance for Doubtful Accounts | B73: 706000 | C73: 515000 | D73: 462000 | E73: 752000 | F73: 870000
A74: CIQ Restatement Type Code | B74: RS | C74: NC | D74: NC | E74: RC | F74: O
A75: CIQ Calculation Type Code | B75: RUP | C75: RUP | D75: RUP | E75: REP | F75: REP
A76: Loss Carry Forward Related Items (R000)
A77: NOL Carryforward, Current Year | B77: 240200 | C77: 3000 | D77: 167000 | E77: 207000 | F77: NA
A78: NOL Carryforward, Current Year + 1 | B78: 240200 | C78: 287500 | D78: 271250 | E78: NA | F78: NA
A79: NOL Carryforward, Current Year + 2 | B79: 240200 | C79: 287500 | D79: 271250 | E79: NA | F79: NA
A80: NOL Carryforward, Current Year + 3 | B80: 240200 | C80: 287500 | D80: 271250 | E80: NA | F80: NA
A81: NOL Carryforward, Current Year + 4 | B81: 240200 | C81: 287500 | D81: 271250 | E81: NA | F81: NA
A82: NOL Carryforward, After Five Years | B82: 19090000 | C82: 608000 | D82: 763000 | E82: 1307000 | F82: 1395000
A83: NOL Carryforward, No Expiration | B83: 716000 | C83: 777000 | D83: 2215000 | E83: 3551000 | F83: 115934000
A84: Total NOL Carryforward | B84: 21007000 | C84: 2538000 | D84: 4230000 | E84: 5065000 | F84: 117329000
A85: Fair Value Measurements (R000)
A86: Level 1 Assets - Quoted Prices | B86: 36627000 | C86: 33119000 | D86: 45151000 | E86: 57311000 | F86: 50079000
A87: Level 2 Assets - Observable Prices | B87: 645000 | C87: 1436000 | D87: 247000 | E87: 472000 | F87: 1297000
A88: Level 3 Assets - Unobservable Prices | B88: 27903000 | C88: 31914000 | D88: 42593000 | E88: 34246000 | F88: 34695000
A89: Fair Value of Assets | B89: 65175000 | C89: 66469000 | D89: 87991000 | E89: 92029000 | F89: 86071000
A90: Level 1 Liabilities - Quoted Prices | B90: 50701000 | C90: 72226000 | D90: 71667000 | E90: 82768000 | F90: 55778000
A91: Level 2 Liabilities - Observable Prices | B91: 7578000 | C91: 4559000 | D91: 6845000 | E91: 3181000 | F91: 4471000
A92: Level 3 Liabilities - Unobservable Prices | B92: 155604000 | C92: 58380000 | D92: 67234000 | E92: 69337000 | F92: 86923000
A93: Fair Value of Liabilities | B93: 213883000 | C93: 135165000 | D93: 145746000 | E93: 155286000 | F93: 147172000
B95: 2020 | C95: 2021 | D95: 2022 | E95: 2023 | F95: 2024
A96: Total Non-Current Assets | B96: 241461000 | C96: 210924000 | D96: 233937000 | E96: 237157000 | F96: 175940000
A97: Total Assets (Including Intangible Assets) | B97: 474535000 | C97: 360743000 | D97: 419548000 | E97: 433838000 | F97: 364980000
A98: Total Equity | B98: 155917000 | C98: 152471000 | D98: 193197000 | E98: 201524000 | F98: 147427000
A99: Total Liabilities | B99: 318618000 | C99: 208272000 | D99: 226351000 | E99: 232314000 | F99: 217553000
A100: Total Equity and Liabilities | B100: 474535000 | C100: 360743000 | D100: 419548000 | E100: 433838000 | F100: 364980000
A261: Cash Flow - Supplementary Statement
A262: Minority Dividends (Ordinary) | B262: 2414102.9 | C262: 2091820.7 | D262: 0 | E262: 0 | F262: 0
A263: Net Intangible Assets Movements | B263: 0 | C263: 0 | D263: 0 | E263: 0 | F263: 0
A264: Preference Shares Issued by the Company | B264: 0 | C264: 0 | D264: 0 | E264: 0 | F264: 0
A265: Share Incentive Trust Options Exercised | B265: 0 | C265: 0 | D265: 0 | E265: 0 | F265: 0
A266: Minority Dividends (Preference) | B266: 0 | C266: 0 | D266: 0 | E266: 0 | F266: 0
A269: Value Added Statement
A270: Number of Employees | B270: 81284 | C270: 87822 | D270: 89092 | E270: 158000 | F270: 145977
A273: Sundry Data Statement
A274: Ordinary Shares in Issue @ Year End Split Adjusted | B274: 13096599 | C274: 13221312 | D274: 13194321 | E274: 13832498 | F274: 14264891
A275: Nr of Ordinary Shares in Issue @ Year End | B275: 13096599 | C275: 13221312 | D275: 13194321 | E275: 13832498 | F275: 14264891
A276: Months Covered by Financial Statements | B276: 12 | C276: 12 | D276: 12 | E276: 12 | F276: 12
A277: Month of Financial Year End | B277: 12 | C277: 12 | D277: 12 | E277: 12 | F277: 12
A278: Inflation Adjusted Other Fixed Asset | B278: 1.4552244e+08 | C278: 1.7397106e+08 | D278: 1.5726946e+08 | E278: 1.3698963e+08 | F278: 1.6952817e+08
A279: Inflation Adjusted Depreciable Fixed Asset | B279: 32202735 | C279: 23936282 | D279: 22636296 | E279: 20723210 | F279: 19292923
A280: No of Quoted Subsidiaries | B280: 0 | C280: 0 | D280: 0 | E280: 0 | F280: 0
...

Sheet SOCF
A1: JSE:SOL
A2: Sasol Group Limited
A4: Cash Flow Statement | B4: ZAR | C4: ZAR | D4: ZAR | E4: ZAR | F4: ZAR
B5: 2020 | C5: 2021 | D5: 2022 | E5: 2023 | F5: 2024
A6: Operating Activities (R000)
A7: Net Income - CF | B7: -91754000 | C7: 9032000 | D7: 38956000 | E7: 8799000 | F7: -44271000
A8: Depreciation & Amort. | B8: 22327000 | C8: 17644000 | D8: 14073000 | E8: 16491000 | F8: 15644000
A9: Impair. of Oil, Gas & Mineral Prop. | B9: -43000 | C9: 6000 | D9: NA | E9: 899000 | F9: 48000
A10: Depreciation & Amort., Total | B10: 22284000 | C10: 17650000 | D10: 14073000 | E10: 17390000 | F10: 15692000
A11: Minority Int. in Earnings | B11: -810000 | C11: -446000 | D11: -859000 | E11: -433000 | F11: -217000
A12: (Gain) Loss From Sale Of Assets | B12: -715000 | C12: -5520000 | D12: -8460000 | E12: -650000 | F12: 480000
A13: Loss On Sale Of Investment | B13: NA | C13: 112000 | D13: NA | E13: NA | F13: NA
A14: Asset Writedown & Restructuring Costs | B14: 112736000 | C14: 28620000 | D14: -1443000 | E14: 33649000 | F14: 74886000
A15: Loss on Equity Investment | B15: 347000 | C15: -814000 | D15: -3128000 | E15: -2623000 | F15: -1758000
A16: Stock-Based Compensation | B16: 1946000 | C16: 1927000 | D16: 1164000 | E16: 1033000 | F16: 986000
A17: Other Operating Activities | B17: -20111000 | C17: -9318000 | D17: 11532000 | E17: -16039000 | F17: -3573000
A18: Change in Acc. Receivable | B18: 6431000 | C18: -7198000 | D18: -9414000 | E18: 9002000 | F18: -3094000
A19: Change In Inventories | B19: 3397000 | C19: -4872000 | D19: -12281000 | E19: 1913000 | F19: -54000
A20: Change in Acc. Payable | B20: -3990000 | C20: 4916000 | D20: 10159000 | E20: -2865000 | F20: -1693000
A21: Cash from Ops. | B21: 29761000 | C21: 34089000 | D21: 40299000 | E21: 49176000 | F21: 37384000
A22: Investing Activity (R000)
A23: Capital Expenditure | B23: -35145000 | C23: -16372000 | D23: -23142000 | E23: -30726000 | F23: -30074000 | J23: 1000
A24: Sale of Property, Plant and Equipment | B24: 678000 | C24: 1322000 | D24: 8484000 | E24: 802000 | F24: 138000
A25: Divestitures | B25: 1226000 | C25: 30210000 | D25: NA | E25: NA | F25: NA
A26: Sale (Purchase) of Intangible assets | B26: -19000 | C26: -3000 | D26: -120000 | E26: -128000 | F26: -85000
A27: Invest. in Marketable & Equity Securt. | B27: 1947000 | C27: 11726000 | D27: -192000 | E27: -182000 | F27: -217000
A28: Other Investing Activities | B28: -7237000 | C28: -1790000 | D28: -107000 | E28: 2000000 | F28: -419000
A29: Cash from Investing | B29: -38550000 | C29: 25093000 | D29: -15077000 | E29: -28234000 | F29: -30657000
A30: Financing Activity (R000)
A31: Short Term Debt Issued | B31: 19998000 | C31: 9000 | D31: 28000 | E31: 1787000 | F31: 2691000
A32: Long-Term Debt Issued | B32: 36487000 | C32: 26057000 | D32: 88000 | E32: 95035000 | F32: 30692000
A33: Total Debt Issued | B33: 56485000 | C33: 26066000 | D33: 116000 | E33: 96822000 | F33: 33383000
A34: Short Term Debt Repaid | B34: -977000 | C34: -19717000 | D34: -15000 | E34: -1801000 | F34: -2183000
A35: Long-Term Debt Repaid | B35: -30396000 | C35: -64614000 | D35: -15054000 | E35: -93833000 | F35: -38166000
A36: Total Debt Repaid | B36: -31373000 | C36: -84331000 | D36: -15069000 | E36: -95634000 | F36: -40349000
A37: Common Dividends Paid | B37: -31000 | C37: -46000 | D37: -49000 | E37: -13754000 | F37: -7633000
A38: Total Dividends Paid | B38: -31000 | C38: -46000 | D38: -49000 | E38: -13754000 | F38: -7633000
A39: Cash from Financing | B39: 25081000 | C39: -58311000 | D39: -15002000 | E39: -12566000 | F39: -14599000
A40: Other Cash Flow (R000)
A41: Foreign Exchange Rate Adj. | B41: 3607000 | C41: -2916000 | D41: 1759000 | E41: 2424000 | F41: -633000
A42: Misc. Cash Flow Adj. | B42: -1624000 | C42: -1061000 | D42: NA | E42: NA | F42: NA
A43: Net Change in Cash | B43: 18275000 | C43: -3106000 | D43: 11979000 | E43: 10800000 | F43: -8505000
A44: Supplemental Items (R000)
A45: Cash Interest Paid | B45: 7154000 | C45: 6173000 | D45: 5478000 | E45: 7083000 | F45: 8638000
A46: Cash Taxes Paid | B46: 5659000 | C46: 5280000 | D46: 13531000 | E46: 13952000 | F46: 10932000
A47: Levered Free Cash Flow | B47: -85179875 | C47: 85308625 | D47: 22117875 | E47: 15911000 | F47: 52662500
A48: Unlevered Free Cash Flow | B48: -80584875 | C48: 89503000 | D48: 25725375 | E48: 21606625 | F48: 6916625
A49: Change in Net Working Capital | B49: 77974000 | C49: -70276000 | D49: -2251000 | E49: -477000 | F49: 7518000
A50: Net Debt Issued | B50: 25112000 | C50: -58265000 | D50: -14953000 | E50: 1188000 | F50: -6966000
A51: CIQ Restatement Type Code | B51: RS | C51: NC | D51: NC | E51: NC | F51: O
A52: CIQ Calculation Type Code | B52: REP | C52: REP | D52: REP | E52: REP | F52: REP
B54: 2020 | C54: 2021 | D54: 2022 | E54: 2023 | F54: 2024
A55: {=A21:F21} -> Cash from Ops. | B55: 29761000 | C55: 34089000 | D55: 40299000 | E55: 49176000 | F55: 37384000
A56: {=A29:F29} -> Cash from Investing | B56: -38550000 | C56: 25093000 | D56: -15077000 | E56: -28234000 | F56: -30657000
A57: {=A39:F39} -> Cash from Financing | B57: 25081000 | C57: -58311000 | D57: -15002000 | E57: -12566000 | F57: -14599000
A58: {=A43:F43} -> Net Change in Cash | B58: 18275000 | C58: -3106000 | D58: 11979000 | E58: 10800000 | F58: -8505000

Sheet Financial Analysis
A1: JSE:SOL (SASOL GROUP LIMITED)
A3: Liquidity | B3: 2020 | C3: 2021 | D3: 2022 | E3: 2023 | F3: 2024
A4: Cash Ratio | B4: =SOFP!B7/SOFP!B35 -> 0.37306428 | C4: =SOFP!C7/SOFP!C35 -> 0.54254395 | D4: =SOFP!D7/SOFP!D35 -> 0.47006265 | E4: =SOFP!E7/SOFP!E35 -> 0.52844278 | F4: =SOFP!F7/SOFP!F35 -> 0.832792
A5: Current Ratio | B5: =SOFP!B16/SOFP!B35 -> 1.9112202 | C5: =SOFP!C16/SOFP!C35 -> 1.8269057 | D5: =SOFP!D16/SOFP!D35 -> 1.4410896 | E5: =SOFP!E16/SOFP!E35 -> 1.3183043 | F5: =SOFP!F16/SOFP!F35 -> 2.3253693
A6: Quick Ratio | B6: =(SOFP!B16-SOFP!B13)/SOFP!B35 -> 1.6126635 | C6: =(SOFP!C16-SOFP!C13)/SOFP!C35 -> 1.3102286 | D6: =(SOFP!D16-SOFP!D13)/SOFP!D35 -> 0.99314628 | E6: =(SOFP!E16-SOFP!E13)/SOFP!E35 -> 0.90472037 | F6: =(SOFP!F16-SOFP!F13)/SOFP!F35 -> 1.5781631
A7: Net working capital to sales | B7: =(SOFP!B16-SOFP!B35)/SOIC!B5 -> 0.44572326 | C7: =(SOFP!C16-SOFP!C35)/SOIC!C5 -> 0.2357486 | D7: =(SOFP!D16-SOFP!D35)/SOIC!D5 -> 0.14842014 | E7: =(SOFP!E16-SOFP!E35)/SOIC!E5 -> 0.11212443 | F7: =(SOFP!F16-SOFP!F35)/SOIC!F5 -> 0.26253403
A8: Interest Coverage ratio | B8: =-SOIC!B54/SOIC!B19 -> 1.8113439 | C8: =-SOIC!C54/SOIC!C19 -> 3.8205931 | D8: =-SOIC!D54/SOIC!D19 -> 8.7316355 | E8: =-SOIC!E54/SOIC!E19 -> 5.8923516 | F8: =-SOIC!F54/SOIC!F19 -> 4.3686424
A10: Cash Flow Analysis | B10: 2020 | C10: 2021 | D10: 2022 | E10: 2023 | F10: 2024
A11: Adequacy Ratio | B11: =(SOIC!B52)/((-SOIC!B19)+(SOFP!B36)) -> 0.22988706 | C11: =(SOIC!C52)/((-SOIC!C19)+(SOFP!C36)) -> 0.41685926 | D11: =(SOIC!D52)/((-SOIC!D19)+(SOFP!D36)) -> 0.73037883 | E11: =(SOIC!E52)/((-SOIC!E19)+(SOFP!E36)) -> 0.75178275 | F11: =(SOIC!F52)/((-SOIC!F19)+(SOFP!F36)) -> 0.45885823
A12: Cash Flow To Current Liabilities | B12: =SOCF!B21/SOFP!B35 -> 0.31960523 | C12: =SOCF!C21/SOFP!C35 -> 0.59219304 | D12: =SOCF!D21/SOFP!D35 -> 0.43910651 | E12: =SOCF!E21/SOFP!E35 -> 0.4818956 | F12: =SOCF!F21/SOFP!F35 -> 0.68600789
A13: Cash Flow To Net Earnings After Tax | B13: =SOCF!B21/SOIC!B34 -> -0.32378124 | C13: =SOCF!C21/SOIC!C34 -> 3.2367072 | D13: =SOCF!D21/SOIC!D34 -> 0.96705222 | E13: =SOCF!E21/SOIC!E34 -> 5.2690453 | F13: =SOCF!F21/SOIC!F34 -> -0.84493163
A14: Cash Flow To Total Debt | B14: =SOCF!B21/SOFP!B57 -> 0.14346177 | C14: =SOCF!C21/SOFP!C57 -> 0.2873726 | D14: =SOCF!D21/SOFP!D57 -> 0.33271138 | E14: =SOCF!E21/SOFP!E57 -> 0.34975072 | F14: =SOCF!F21/SOFP!F57 -> 0.27660094
A15: Cash Flow To Turnover (Margin) | B15: =SOCF!B21/SOIC!B5 -> 0.15633487 | C15: =SOCF!C21/SOIC!C5 -> 0.16883265 | D15: =SOCF!D21/SOIC!D5 -> 0.14775285 | E15: =SOCF!E21/SOIC!E5 -> 0.16975036 | F15: =SOCF!F21/SOIC!F5 -> 0.13588697
A16: Cash Flow To All Investments | B16: =SOCF!B21+SOCF!B29+SOCF!B39/((-SOCF!B23)+(-SOCF!B26)+(-SOCF!B28)) -> -8788999.4 | C16: =SOCF!C21+SOCF!C29+SOCF!C39/((-SOCF!C23)+(-SOCF!C26)+(-SOCF!C28)) -> 59181997 | D16: =SOCF!D21+SOCF!D29+SOCF!D39/((-SOCF!D23)+(-SOCF!D26)+(-SOCF!D28)) -> 25221999 | E16: =SOCF!E21+SOCF!E29+SOCF!E39/((-SOCF!E23)+(-SOCF!E26)+(-SOCF!E28)) -> 20942000 | F16: =SOCF!F21+SOCF!F29+SOCF!F39/((-SOCF!F23)+(-SOCF!F26)+(-SOCF!F28)) -> 6726999.5
A17: Cash Flow To Capital Investments | B17: =SOCF!B21+SOCF!B29+SOCF!B39/ABS(SOCF!B23) -> -8788999.3 | C17: =SOCF!C21+SOCF!C29+SOCF!C39/ABS(SOCF!C23) -> 59181996 | D17: =SOCF!D21+SOCF!D29+SOCF!D39/ABS(SOCF!D23) -> 25221999 | E17: =SOCF!E21+SOCF!E29+SOCF!E39/ABS(SOCF!E23) -> 20942000 | F17: =SOCF!F21+SOCF!F29+SOCF!F39/ABS(SOCF!F23) -> 6726999.5
A18: Cash Flow To Financial Investments | B18: =SOCF!B21+SOCF!B29+SOCF!B39/-SOCF!B28 -> -8788996.5 | C18: =SOCF!C21+SOCF!C29+SOCF!C39/-SOCF!C28 -> 59181967 | D18: =SOCF!D21+SOCF!D29+SOCF!D39/-SOCF!D28 -> 25221860 | E18: =SOCF!E21+SOCF!E29+SOCF!E39/-SOCF!E28 -> 20942006 | F18: =SOCF!F21+SOCF!F29+SOCF!F39/-SOCF!F28 -> 6726965.2
A19: Cash Flow Less Interest Paid To Income Before Tax | B19: =(SOCF!B21-SOCF!B45)/SOIC!B30 -> -0.19108759 | C19: =(SOCF!C21-SOCF!C45)/SOIC!C30 -> 2.6048334 | D19: =(SOCF!D21-SOCF!D45)/SOIC!D30 -> 0.62694226 | E19: =(SOCF!E21-SOCF!E45)/SOIC!E30 -> 2.9001654 | F19: =(SOCF!F21-SOCF!F45)/SOIC!F30 -> -0.83307251
A20: Cash Flow Return On Total Net Assets | B20: =SOCF!B21/SOFP!B49 -> 0.1908772 | C20: =SOCF!C21/SOFP!C49 -> 0.22357694 | D20: =SOCF!D21/SOFP!D49 -> 0.2085902 | E20: =SOCF!E21/SOFP!E49 -> 0.24402056 | F20: =SOCF!F21/SOFP!F49 -> 0.25357635
A21: Cash Flow To Capital Redemption | B21: =SOCF!B21/ABS(SOCF!B36) -> 0.94861824 | C21: =SOCF!C21/ABS(SOCF!C36) -> 0.40422858 | D21: =SOCF!D21/ABS(SOCF!D36) -> 2.6742982 | E21: =SOCF!E21/ABS(SOCF!E36) -> 0.51421043 | F21: =SOCF!F21/ABS(SOCF!F36) -> 0.92651615
A22: Dividend Coverage | B22: =SOCF!B21/ABS(SOCF!B38) -> 960.03226 | C22: =SOCF!C21/ABS(SOCF!C38) -> 741.06522 | D22: =SOCF!D21/ABS(SOCF!D38) -> 822.42857 | E22: =SOCF!E21/ABS(SOCF!E38) -> 3.5753962 | F22: =SOCF!F21/ABS(SOCF!F38) -> 4.8976811
A23: Interest Coverage | B23: =SOIC!B54/ABS(SOIC!B19) -> 1.8113439 | C23: =SOIC!C54/ABS(SOIC!C19) -> 3.8205931 | D23: =SOIC!D54/ABS(SOIC!D19) -> 8.7316355 | E23: =SOIC!E54/ABS(SOIC!E19) -> 5.8923516 | F23: =SOIC!F54/ABS(SOIC!F19) -> 4.3686424
A24: Reinvestment Rate | B24: =((-SOCF!B23)+(-SOCF!B26))/SOCF!B21 -> 1.1815463 | C24: =((-SOCF!C23)+(-SOCF!C26))/SOCF!C21 -> 0.48036023 | D24: =((-SOCF!D23)+(-SOCF!D26))/SOCF!D21 -> 0.57723517 | E24: =((-SOCF!E23)+(-SOCF!E26))/SOCF!E21 -> 0.62741988 | F24: =((-SOCF!F23)+(-SOCF!F26))/SOCF!F21 -> 0.8067355
A26: Operating profitability indicators | B26: 2020 | C26: 2021 | D26: 2022 | E26: 2023 | F26: 2024
A27: Return On Assets % | B27: =(SOIC!B34/SOFP!B25)*100 -> -19.369909 | C27: =(SOIC!C34/SOFP!C25)*100 -> 2.91953 | D27: =(SOIC!D34/SOFP!D25)*100 -> 9.9325941 | E27: =(SOIC!E34/SOFP!E25)*100 -> 2.1512638 | F27: =(SOIC!F34/SOFP!F25)*100 -> -12.122582
A28: Return On Average Assets % | B28: =(SOIC!B34/SOFP!B25) *100 -> -19.369909 | C28: =SOIC!C34/((SOFP!B25+SOFP!C25)/2) *100 -> 2.5217951 | D28: =SOIC!D34/((SOFP!C25+SOFP!D25)/2) *100 -> 10.681143 | E28: =SOIC!E34/((SOFP!D25+SOFP!E25)/2) *100 -> 2.1872869 | F28: =SOIC!F34/((SOFP!E25+SOFP!F25)/2) *100 -> -11.077617
A29: Return On Average Equity % | B29: - | C29: =SOIC!C34/((SOFP!B49+SOFP!C49)/2) *100 -> 6.8303566 | D29: =SOIC!D34/((SOFP!C49+SOFP!D49)/2) *100 -> 24.110997 | E29: =SOIC!E34/((SOFP!D49+SOFP!E49)/2) *100 -> 4.7289098 | F29: =SOIC!F34/((SOFP!E49+SOFP!F49)/2) *100 -> -25.358861
A30: Return On Capital Employed % | B30: =(SOIC!B54/SOFP!B49)*100 -> 8.5410828 | C30: =(SOIC!C54/SOFP!C49)*100 -> 16.816313 | D30: =(SOIC!D54/SOFP!D49)*100 -> 26.086844 | E30: =(SOIC!E54/SOFP!E49)*100 -> 26.645462 | F30: =(SOIC!F54/SOFP!F49)*100 -> 30.29635
A31: Return On Equity % | B31: - | C31: =SOIC!C34/((SOFP!B47+SOFP!C47)/2)*100 -> 7.0811692 | D31: =SOIC!D34/((SOFP!C47+SOFP!D47)/2)*100 -> 24.870491 | E31: =SOIC!E34/((SOFP!D47+SOFP!E47)/2)*100 -> 4.8416842 | F31: =SOIC!F34/((SOFP!E47+SOFP!F47)/2)*100 -> -26.033438
A32: Total Assets Turnover | B32: - | C32: =(SOIC!C5/(SOFP!B25+SOFP!C25)/2)*100 -> 12.086395 | D32: =(SOIC!D5/(SOFP!C25+SOFP!D25)/2)*100 -> 17.477198 | E32: =(SOIC!E5/(SOFP!D25+SOFP!E25)/2)*100 -> 16.973327 | F32: =(SOIC!F5/(SOFP!E25+SOFP!F25)/2)*100 -> 17.21988
A33: Total Debt / Cash Flow | B33: =(SOFP!B57/SOCF!B21)*100 -> 697.04983 | C33: =(SOFP!C57/SOCF!C21)*100 -> 347.98029 | D33: =(SOFP!D57/SOCF!D21)*100 -> 300.56081 | E33: =(SOFP!E57/SOCF!E21)*100 -> 285.91793 | F33: =(SOFP!F57/SOCF!F21)*100 -> 361.53167
A34: Turnover / Employee | B34: =(SOIC!B5/SOFP!B72)*100 -> 620694.49 | C34: =(SOIC!C5/SOFP!C72)*100 -> 702906.88 | D34: =(SOIC!D5/SOFP!D72)*100 -> 964482.48 | E34: =(SOIC!E5/SOFP!E72)*100 -> 1010908.3 | F34: =(SOIC!F5/SOFP!F72)*100 -> 993969.94
A36: Operating Efficiency | B36: 2020 | C36: 2021 | D36: 2022 | E36: 2023 | F36: 2024
A37: Inventory turnover | B37: =SOIC!B7/SOFP!B13 -> 3.6186468 | C37: =SOIC!C7/SOFP!C13 -> 3.2776881 | D37: =SOIC!D7/SOFP!D13 -> 3.3403308 | E37: =SOIC!E7/SOFP!E13 -> 3.965715 | F37: =SOIC!F7/SOFP!F13 -> 3.7673568
A38: Fixed assets turnover | B38: =SOIC!B5/SOFP!B19 -> 0.78839647 | C38: =SOIC!C5/SOFP!C19 -> 0.95726423 | D38: =SOIC!D5/SOFP!D19 -> 1.1658951 | E38: =SOIC!E5/SOFP!E19 -> 1.2215368 | F38: =SOIC!F5/SOFP!F19 -> 1.5636637
A39: Total asset turnover | B39: =SOIC!B5/SOFP!B25 -> 0.40116535 | C39: =SOIC!C5/SOFP!C25 -> 0.55970594 | D39: =SOIC!D5/SOFP!D25 -> 0.65009486 | E39: =SOIC!E5/SOFP!E25 -> 0.66775156 | F39: =SOIC!F5/SOFP!F25 -> 0.75377007
A40: Trade receivables turnover time (days) | B40: =(SOFP!B12/SOIC!B5)*365 -> 55.43248 | C40: =(((SOFP!B12+SOFP!C12)/2)/SOIC!C5)*365 -> 53.415891 | D40: =(((SOFP!C12+SOFP!D12)/2)/SOIC!D5)*365 -> 50.501217 | E40: =(((SOFP!D12+SOFP!E12)/2)/SOIC!E5)*365 -> 49.828795 | F40: =(((SOFP!E12+SOFP!F12)/2)/SOIC!F5)*365 -> 45.934959
A41: Total Debt / Cash Flow | B41: =SOFP!B57/SOCF!B21 -> 6.9704983 | C41: =SOFP!C57/SOCF!C21 -> 3.4798029 | D41: =SOFP!D57/SOCF!D21 -> 3.0056081 | E41: =SOFP!E57/SOCF!E21 -> 2.8591793 | F41: =SOFP!F57/SOCF!F21 -> 3.6153167
A43: Financial Leverage | B43: 2020 | C43: 2021 | D43: 2022 | E43: 2023 | F43: 2024
A44: Leverage factor | B44: =SOFP!B25/SOFP!B49 -> 3.0435103 | C44: =SOFP!C25/SOFP!C49 -> 2.3659778 | D44: =SOFP!D25/SOFP!D49 -> 2.1716072 | E44: =SOFP!E25/SOFP!E49 -> 2.1527858 | F44: =SOFP!F25/SOFP!F49 -> 2.4756659
A45: Debt ratio | B45: =SOFP!B42/SOFP!B25 -> 0.67143203 | C45: =SOFP!C42/SOFP!C25 -> 0.57734176 | D45: =SOFP!D42/SOFP!D25 -> 0.53951157 | E45: =SOFP!E42/SOFP!E25 -> 0.5354856 | F45: =SOFP!F42/SOFP!F25 -> 0.59606828
A46: Debt to equity ratio | B46: =SOFP!B57/SOFP!B49 -> 1.3305092 | C46: =SOFP!C57/SOFP!C49 -> 0.77800369 | D46: =SOFP!D57/SOFP!D49 -> 0.62694038 | E46: =SOFP!E57/SOFP!E49 -> 0.69769854 | F46: =SOFP!F57/SOFP!F49 -> 0.9167588
A47: Interest coverage ratio | B47: =SOIC!B54/ABS(SOIC!B19) -> 1.8113439 | C47: =SOIC!C54/ABS(SOIC!C19) -> 3.8205931 | D47: =SOIC!D54/ABS(SOIC!D19) -> 8.7316355 | E47: =SOIC!E54/ABS(SOIC!E19) -> 5.8923516 | F47: =SOIC!F54/ABS(SOIC!F19) -> 4.3686424
A48: Equity ratio | B48: =SOFP!B49/SOFP!B25 -> 0.32856797 | C48: =SOFP!C49/SOFP!C25 -> 0.42265824 | D48: =SOFP!D49/SOFP!D25 -> 0.46048843 | E48: =SOFP!E49/SOFP!E25 -> 0.4645144 | F48: =SOFP!F49/SOFP!F25 -> 0.40393172
A49: Interest burden | B49: =SOIC!B30/SOIC!B54 -> -8.8839078 | C49: =SOIC!C30/SOIC!C54 -> 0.41797972 | D49: =SOIC!D30/SOIC!D54 -> 1.1020258 | E49: =SOIC!E30/SOIC!E54 -> 0.27029443 | F49: =SOIC!F30/SOIC!F54 -> -0.77255121
A50: Equity Multiplier | B50: =SOFP!B25/SOFP!B49 -> 3.0435103 | C50: =SOFP!C25/SOFP!C49 -> 2.3659778 | D50: =SOFP!D25/SOFP!D49 -> 2.1716072 | E50: =SOFP!E25/SOFP!E49 -> 2.1527858 | F50: =SOFP!F25/SOFP!F49 -> 2.4756659
A52: Shareholders indicators | B52: 2020 | C52: 2021 | D52: 2022 | E52: 2023 | F52: 2024
A53: Shareholders equity | B53: =SOFP!B49 -> 155917000 | C53: =SOFP!C49 -> 152471000 | D53: =SOFP!D49 -> 193197000 | E53: =SOFP!E49 -> 201524000 | F53: =SOFP!F49 -> 147427000
A54: No. of outstanding shares | B54: =SOFP!B53 -> 627887189 | C54: =SOFP!C53 -> 629765768 | D54: =SOFP!D53 -> 631203721 | E54: =SOFP!E53 -> 630293924 | F54: =SOFP!F53 -> 635419278
A55: Earnings / Share (c) | B55: =(SOIC!B34/SOFP!B53)*100 -> -14.639095 | C55: =(SOIC!C34/SOFP!C53)*100 -> 1.6723678 | D55: =(SOIC!D34/SOFP!D53)*100 -> 6.601989 | E55: =(SOIC!E34/SOFP!E53)*100 -> 1.4807377 | F55: =(SOIC!F34/SOFP!F53)*100 -> -6.9631189
A56: Earnings Yield % | B56: =(B55/8217)*100 -> -0.1781562 | C56: =(C55/8217)*100 -> 0.020352535 | D56: =(D55/8217)*100 -> 0.080345491 | E56: =(E55/8217)*100 -> 0.018020418 | F56: =(F55/8217)*100 -> -0.084740403
A58: Growth potential | B58: 2020 | C58: 2021 | D58: 2022 | E58: 2023 | F58: 2024
A59: Enterprise Value / Cash | B59: =(SOFP!I53+SOFP!B57-SOFP!B7)/SOFP!B7 -> 2394.4096 | C59: =(SOFP!J53+SOFP!C57-SOFP!C7)/SOFP!C7 -> 4398.9186 | D59: =(SOFP!K53+SOFP!D57-SOFP!D7)/SOFP!D7 -> 5440.0506 | E59: =(SOFP!L53+SOFP!E57-SOFP!E7)/SOFP!E7 -> 2727.9798 | F59: =(SOFP!M53+SOFP!F57-SOFP!F7)/SOFP!F7 -> 1934.1523
A60: Enterprise Value / EBIT | B60: =(SOFP!I53+SOFP!B57-SOFP!B7)/'Financial Analysis'!B54 -> 132.47507 | C60: =(SOFP!J53+SOFP!C57-SOFP!C7)/'Financial Analysis'!C54 -> 218.14877 | D60: =(SOFP!K53+SOFP!D57-SOFP!D7)/'Financial Analysis'!D54 -> 371.80355 | E60: =(SOFP!L53+SOFP!E57-SOFP!E7)/'Financial Analysis'!E54 -> 233.39752 | F60: =(SOFP!M53+SOFP!F57-SOFP!F7)/'Financial Analysis'!F54 -> 138.14128
A61: Enterprise Value / EBITDA | B61: =(SOFP!I53+SOFP!B57-SOFP!B7)/SOIC!B52 -> 2336.4343 | C61: =(SOFP!J53+SOFP!C57-SOFP!C7)/SOIC!C52 -> 3173.5419 | D61: =(SOFP!K53+SOFP!D57-SOFP!D7)/SOIC!D52 -> 3640.0884 | E61: =(SOFP!L53+SOFP!E57-SOFP!E7)/SOIC!E52 -> 2140.1725 | F61: =(SOFP!M53+SOFP!F57-SOFP!F7)/SOIC!F52 -> 1516.5713
A62: Enterprise Value / PAT | B62: =(SOFP!I53+SOFP!B57-SOFP!B7)/SOIC!B34 -> -904.94029 | C62: =(SOFP!J53+SOFP!C57-SOFP!C7)/SOIC!C34 -> 13044.306 | D62: =(SOFP!K53+SOFP!D57-SOFP!D7)/SOIC!D34 -> 5631.6899 | E62: =(SOFP!L53+SOFP!E57-SOFP!E7)/SOIC!E34 -> 15762.246 | F62: =(SOFP!M53+SOFP!F57-SOFP!F7)/SOIC!F34 -> -1983.8995
A63: Enterprise Value / Share | B63: =(SOFP!I53+SOFP!B57-SOFP!B7)/SOFP!B53 -> 132.47507 | C63: =(SOFP!J53+SOFP!C57-SOFP!C7)/SOFP!C53 -> 218.14877 | D63: =(SOFP!K53+SOFP!D57-SOFP!D7)/SOFP!D53 -> 371.80355 | E63: =(SOFP!L53+SOFP!E57-SOFP!E7)/SOFP!E53 -> 233.39752 | F63: =(SOFP!M53+SOFP!F57-SOFP!F7)/SOFP!F53 -> 138.14128
A64: Attributable Earnings | B64: =SOIC!B36 -> -91754000 | C64: =SOIC!C36 -> 9032000 | D64: =SOIC!D36 -> 38956000 | E64: =SOIC!E36 -> 8799000 | F64: =SOIC!F36 -> -44271000
A65: Earnings / Share | B65: =(SOIC!B34/SOFP!B53)*100 -> -14.639095 | C65: =(SOIC!C34/SOFP!C53)*100 -> 1.6723678 | D65: =(SOIC!D34/SOFP!D53)*100 -> 6.601989 | E65: =(SOIC!E34/SOFP!E53)*100 -> 1.4807377 | F65: =(SOIC!F34/SOFP!F53)*100 -> -6.9631189
A66: Growth In Cash From Operating Activities | C66: =((SOCF!C21-SOCF!B21)/SOCF!B21)*100 -> 14.542522 | D66: =((SOCF!D21-SOCF!C21)/SOCF!C21)*100 -> 18.21702 | E66: =((SOCF!E21-SOCF!D21)/SOCF!D21)*100 -> 22.027842 | F66: =((SOCF!F21-SOCF!E21)/SOCF!E21)*100 -> -23.979177
A67: Net Turnover growth | B67: - | C67: =SOIC!C6 -> 6.0635509 | D67: =SOIC!D6 -> 35.082958 | E67: =SOIC!E6 -> 6.2145733 | F67: =SOIC!F6 -> -5.034588
A68: Total Assets growth | B68: - | C68: =((SOFP!C25-SOFP!B25)/SOFP!B25)*100 -> -23.979685 | D68: =((SOFP!D25-SOFP!C25)/SOFP!C25)*100 -> 16.301079 | E68: =((SOFP!E25-SOFP!D25)/SOFP!D25)*100 -> 3.4060465 | F68: =((SOFP!F25-SOFP!E25)/SOFP!E25)*100 -> -15.871823
A69: Total Shareholders Interest | B69: - | C69: =((SOFP!C49-SOFP!B49)/SOFP!B49)*100 -> -2.2101503 | D69: =((SOFP!D49-SOFP!C49)/SOFP!C49)*100 -> 26.710653 | E69: =((SOFP!E49-SOFP!D49)/SOFP!D49)*100 -> 4.3101083 | F69: =((SOFP!F49-SOFP!E49)/SOFP!E49)*100 -> -26.843949
A104: Force | B104: Score%
A105: New Entrants | B105: 0.35
A106: Suppliers | B106: 0.56
A107: Power of Buyers | B107: 0.69
A108: Substituions | B108: 0.85
A109: Industry rivals | B109: 0.95

Sheet valuation
A1: FCFF
A2: Base Case Assumptions | F2: Net Debt (2024) | G2: =(SOFP!F57-SOFP!F7)*1000 -> 89772000000 | I2: ECS Total Common Shares Outstanding (actual) | J2: 63541927800
A3: WACC | B3: 0.14 | C3: SA risk premium and Sasols Beta
A4: Terminal Growth | B4: 0.025 | C4: SA GDP + Inflation
A5: Tax rate | B5: 0.28 | C5: SA corporate rate
A6: maintanence Capex | B6: 0.7
A7: change in NWZ of change in Revenue | B7: 0.08
A8: Depreciation | B8: R14.5 billion
A11: Projections
A12: year | B12: Revenue | C12: EBITDA Margin | D12: EBITDA | E12: EBIT | F12: TAX | G12: NOPAT | H12: D&A | I12: CAPEX | J12: CHANGE NWC | K12: FCFF | L12: Terminal Value | M12: Present value FCFF | N12: pv of terminal value | O12: Equity Value | P12: intrinsic value per share
A13: 2025 | B13: 2916186600000 | C13: 0.21 | D13: =B13*C13 -> 612399186000 | E13: =D13-H13 -> 597899186000 | F13: =E13*B5 -> 1.6741177e+11 | G13: =E13-F13 -> 430487413920 | H13: 14500000000 | I13: =B6*H13 -> 10150000000 | J13: =0.08*(B13 - SOIC!F5) -> 233272919120 | K13: =G13+H13-I13-J13 -> 201564494800 | L13: =(K13*(1+0.025))/(0.14-0.025) -> 1.7965531e+12 | M13: =K13/((1+0.14)^1) -> 1.7681096e+11 | N13: =L13/(1+0.14)^1 -> 1.5759238e+12 | O13: =M20-G2 -> 1.1715013e+13 | P13: =O13/J2 -> 184.36666
A14: 2026 | B14: =B13 * 1.06 -> 3091157796000 | C14: 0.215 | D14: =B14*C14 -> 664598926140 | E14: =D14-H14 -> 650098926140 | F14: =E14*B5 -> 1.820277e+11 | G14: =E14-F14 -> 4.6807123e+11 | H14: 14500000000 | I14: =0.7 * H14 -> 10150000000 | J14: =0.8*(B14-B13) -> 139976956800 | K14: =G14+H14-I14-J14 -> 3.3244427e+11 | L14: =(K14*(1+0.025))/(0.14-0.025) -> 2.9630902e+12 | M14: =K14/(1+0.14)^2 -> 2.5580507e+11 | N14: =L14/(1+0.14)^2 -> 2.2800017e+12
A15: 2027 | B15: =B14 * 1.05 -> 3245715685800 | C15: 0.22 | D15: =B15*C15 -> 714057450876 | E15: =D15-H15 -> 699557450876 | F15: =E15*B5 -> 1.9587609e+11 | G15: =E15-F15 -> 5.0368136e+11 | H15: 14500000000 | I15: =0.7 * H15 -> 10150000000 | J15: =0.8*(B15-B14) -> 123646311840 | K15: =G15+H15-I15-J15 -> 3.8438505e+11 | L15: =(K15*(1+0.025))/(0.14-0.025) -> 3.4260407e+12 | M15: =K15/(1+0.14)^3 -> 2.5944896e+11 | N15: =L15/(1+0.14)^3 -> 2.3124799e+12
A16: 2028 | B16: =B15 * 1.04 -> 3375544313232 | C16: 0.22 | D16: =B16*C16 -> 7.4261975e+11 | E16: =D16-H16 -> 7.2811975e+11 | F16: =E16*B5 -> 2.0387353e+11 | G16: =E16-F16 -> 5.2424622e+11 | H16: 14500000000 | I16: =0.7 * H16 -> 10150000000 | J16: =0.8*(B16-B15) -> 1.038629e+11 | K16: =G16+H16-I16-J16 -> 4.2473332e+11 | L16: =(K16*(1+0.025))/(0.14-0.025) -> 3.7856665e+12 | M16: =K16/(1+0.14)^4 -> 2.5147622e+11 | N16: =L16/(1+0.14)^4 -> 2.2414185e+12
A17: 2029 | B17: =B16* 1.03 -> 3.4768106e+12 | C17: 0.225 | D17: =B17*C17 -> 7.8228239e+11 | E17: =D17-H17 -> 7.6778239e+11 | F17: =E17*B5 -> 2.1497907e+11 | G17: =E17-F17 -> 5.5280332e+11 | H17: 14500000000 | I17: =0.7 * H17 -> 10150000000 | J17: =0.8*(B17-B16) -> 8.1013064e+10 | K17: =G17+H17-I17-J17 -> 4.7614026e+11 | L17: =(K17*(1+0.025))/(0.14-0.025) -> 4.2438588e+12 | M17: =K17/(1+0.14)^5 -> 2.4729233e+11 | N17: =L17/(1+0.14)^5 -> 2.2041273e+12
L19: sum | M19: =SUM(M13:M17) -> 1.1908335e+12 | N19: =SUM(N13:N17) -> 1.0613951e+13
L20: enterprise value | M20: =SUM(M19:N19) -> 1.1804785e+13
A24: Gordon Growth Model
A25: Base assumptions
A26: Levered Free Cash Flow | B26: 52662500000 | C26: from the cash flow statement
A27: Growth | B27: 0.025 | C27: base situation
A28: Cost of Equity | B28: 0.165 | C28: CAPM RF=9% + B1.2*6.25
A30: Expected Levered Free cashflow | B30: Expected Levered Free cashflow | C30: Equity Value | D30: intrinsic value
A31: 2025 | B31: =52662500000*(1*2.5%) -> 1316562500 | C31: =B31/(0.165-0.025) -> 9.4040179e+09 | D31: =C31/635419278 -> 14.799705
A32: 2026 | B32: =B31*(1+0.025) -> 1.3494766e+09
A33: 2027 | B33: =B32*(1+0.025) -> 1.3832135e+09
A34: 2028 | B34: =B33*(1+0.025) -> 1.4177938e+09
A35: 2029 | B35: =B34*(1+0.025) -> 1.4532387e+09
